github_token_app/__init__.py
github_token_app/cli.py
github_token_app/github_app.py
github_token_app/py.typed
github_token_app-0.2.0.dist-info/LICENSE
github_token_app-0.2.0.dist-info/METADATA
github_token_app-0.2.0.dist-info/WHEEL
github_token_app-0.2.0.dist-info/entry_points.txt
github_token_app-0.2.0.dist-info/top_level.txt
github_token_app-0.2.0.dist-info/RECORD
