Metadata-Version: 2.1
Name: github-token-app
Version: 0.2.0
Summary: A github app wrapper to generate short lived token
Home-page: https://github.com/mercari/github-token-app
Author: Mercari
License: UNKNOWN
Platform: UNKNOWN
Requires-Dist: github3.py
Requires-Dist: typer
